odoo/addons/l10n_br_sale_blanket_order/README.rst
odoo/addons/l10n_br_sale_blanket_order/__init__.py
odoo/addons/l10n_br_sale_blanket_order/__manifest__.py
odoo/addons/l10n_br_sale_blanket_order/demo/l10n_br_sale_blanket_order.xml
odoo/addons/l10n_br_sale_blanket_order/i18n/l10n_br_sale_blanket_order.pot
odoo/addons/l10n_br_sale_blanket_order/i18n/pt_BR.po
odoo/addons/l10n_br_sale_blanket_order/models/__init__.py
odoo/addons/l10n_br_sale_blanket_order/models/sale_blanket_order.py
odoo/addons/l10n_br_sale_blanket_order/models/sale_blanket_order_line.py
odoo/addons/l10n_br_sale_blanket_order/readme/CONTRIBUTORS.md
odoo/addons/l10n_br_sale_blanket_order/readme/DESCRIPTION.md
odoo/addons/l10n_br_sale_blanket_order/readme/USAGE.md
odoo/addons/l10n_br_sale_blanket_order/static/description/icon.png
odoo/addons/l10n_br_sale_blanket_order/static/description/index.html
odoo/addons/l10n_br_sale_blanket_order/tests/__init__.py
odoo/addons/l10n_br_sale_blanket_order/tests/test_l10n_br_sale_blanket_order.py
odoo/addons/l10n_br_sale_blanket_order/views/sale_blanket_order.xml
odoo/addons/l10n_br_sale_blanket_order/views/sale_blanket_order_line.xml
odoo/addons/l10n_br_sale_blanket_order/wizards/__init__.py
odoo/addons/l10n_br_sale_blanket_order/wizards/sale_blanket_order_wizard.py
odoo_addon_l10n_br_sale_blanket_order-16.0.2.0.0.dist-info/METADATA
odoo_addon_l10n_br_sale_blanket_order-16.0.2.0.0.dist-info/WHEEL
odoo_addon_l10n_br_sale_blanket_order-16.0.2.0.0.dist-info/top_level.txt
odoo_addon_l10n_br_sale_blanket_order-16.0.2.0.0.dist-info/RECORD
