Metadata-Version: 2.1
Name: odoo-addon-l10n_br_sale_blanket_order
Version: 16.0.2.0.0
Requires-Python: >=3.10
Requires-Dist: odoo-addon-l10n_br_sale>=16.0dev,<16.1dev
Requires-Dist: odoo-addon-sale_blanket_order>=16.0dev,<16.1dev
Requires-Dist: odoo>=16.0a,<16.1dev
Summary: Brazilian Localization Sale Blanket Order
Home-page: https://github.com/OCA/l10n-brazil
License: AGPL-3
Author: Escodoo,Odoo Community Association (OCA)
Author-email: support@odoo-community.org
Classifier: Programming Language :: Python
Classifier: Framework :: Odoo
Classifier: Framework :: Odoo :: 16.0
Classifier: License :: OSI Approved :: GNU Affero General Public License v3
